<?xml version="1.0"?>
<!-- Validation and verification of test cases, given a list of CAS files
-->
<validation xref="case" rank="2">

<!-- Extras and Meta Data ~~~~~~~~~~~~~~~~~~~~~~~~~~~~~~~~~~~~~~~~~~
   /!\ This section is being ignored at the moment -->
   <deco xref="default">
      <look format="png" colourbar="jet.xml" />
      <data title="friction" author="artemis" contact="www.opentelemac.org" />
   </deco>

<!-- Python sub-scripts ~~~~~~~~~~~~~~~~~~~~~~~~~~~~~~~~~~~~~~~~~~~~
-->
   <cast xref="fcts" >
      <python>
def mapdiff(a1,a2):
   return a1.support,a2.values-a1.values
def maxdiff(d0):
   a0 = max(np.ravel(d0.values))
   if a0 > 0.0:
      a1 = np.argwhere(d0.values == a0)[-1]
      return "for instance value="+repr(a0)+" at time: "+str(a1[0])+" for variable: "+str(a1[1])+" at node: "+str(a1[2])
   a0 = min(np.ravel(d0.values))
   if 0.0 > a0:
      a1 = np.argwhere(d0.values == a0)[-1]
      return "for instance value="+repr(a0)+" at time: "+str(a1[0])+" for variable: "+str(a1[1])+" at node: "+str(a1[2])
   return "My work has been validated"
      </python>
   </cast>

<!-- Actions on CAS files ~~~~~~~~~~~~~~~~~~~~~~~~~~~~~~~~~~~~~~~~~~
   /!\ do="cas;princi" are being ignored at the moment
   <action xref="2"   ncsize="4"
       do="translate;run;cas;princi"
       code="artemis" target="art_friction.cas"
       title="friction scalar mode"
   />
-->
   <action xref="1"
       do="translate;run;cas;princi"
       code="artemis" target="art_friction.cas"
       title="friction scalar mode"
   />

<!-- Check on Reference File ~~~~~~~~~~~~~~~~~~~~~~~~~~~~~~~~~~~~~~~
-->
   <cast xref="frt-art" config="oneofall" time="[-1]" type="2d:">
      <v1 vars="VE:map" target="1:ARTRES" />
      <v2 vars="VE:map" target="1:ARTREF" />
      <v3 vars="mapdiff(v1,v2)" />
      <return title="Comparison with the last time frame of the reference file."
         fail="max(v3.values.ravel()) > 1.e-6"
         warn="max(v3.values.ravel()) > 1.e-12"
         value="maxdiff(v3)" />
   </cast>

<!-- Check on Parallelisation ~~~~~~~~~~~~~~~~~~~~~~~~~~~~~~~~~~~~~~
   <cast xref="art-art" config="oneofall" time="[-1]" type="2d:">
      <v1 vars="VE:map" target="1:ARTRES" />
      <v2 vars="VE:map" target="2:ARTRES" />
      <v4 vars="mapdiff(v1,v2)" />
      <return title="Comparison with the last time frame of the parallel file."
         fail="max(v4.values.ravel()) > 1.e-6"
         warn="max(v4.values.ravel()) > 1.e-12"
         value="maxdiff(v4)" />
   </cast>
-->

<!-- plot1d ~~~~~~~~~~~~~~~~~~~~~~~~~~~~~~~~~~~~~~~~~~~~~~~~~~~~~~~~
   -->
  <plot1d xref="Section" type="v-section" config="together" size="(10;7)" >
      <layer vars="wave height:line" extract="(0;0.6)(19.9;0.6)" time="[0]" target="1:ARTRES" />
   </plot1d>

<!-- plot2d ~~~~~~~~~~~~~~~~~~~~~~~~~~~~~~~~~~~~~~~~~~~~~~~~~~~~~~~~
  -->
   <plot2d xref="Mesh" size="(12;4)" >
      <layer vars="maillage:mesh" target="1:ARTGEO" config="oneofall" />
   </plot2d>
   <plot2d xref="Wave height" size="(12;4)" >
      <layer vars="wave height:map" target="1:ARTRES" config="oneofall" />
   </plot2d>
   <plot2d xref="Free Surface" size="(12;4)" >
      <layer vars="free surface:map" time="[-1]" target="1:ARTRES" config="oneofall" />
   </plot2d>

</validation>
